AUTHORS
LICENSE
MANIFEST.in
README
VERSION
requirements.txt
setup.py
plugin_manager.egg-info/PKG-INFO
plugin_manager.egg-info/SOURCES.txt
plugin_manager.egg-info/dependency_links.txt
plugin_manager.egg-info/pbr.json
plugin_manager.egg-info/top_level.txt
pluginmanager/__init__.py
pluginmanager/core/__init__.py
pluginmanager/core/config.py
pluginmanager/core/parameter.py
pluginmanager/core/plugin.py
pluginmanager/plugins/__init__.py
pluginmanager/plugins/example.py