Metadata-Version: 1.0
Name: plugin-manager
Version: 0.2
Summary: plugin-manager
Home-page: https://github.com/lvjiyong
Author: lvjiyong
Author-email: lvjiyong@gmail.com
License: GPL
Platform: any
